dun/__init__.py
dun/__main__.py
dun/app.py
dun/cli.py
dun/config/settings.py
dun/core/contexts/__init__.py
dun/core/engine/__init__.py
dun/core/engine/processor_engine.py
dun/core/protocols/__init__.py
dun/llm_analyzer.py
dun/processor_engine.py
dun/services/diagnostics/__init__.py
dun/services/filesystem/__init__.py
dun/services/ollama/__init__.py
dun/services/processors/__init__.py
dun/services/processors/csv_processor.py
dun-0.1.16.dist-info/LICENSE
dun-0.1.16.dist-info/METADATA
dun-0.1.16.dist-info/WHEEL
dun-0.1.16.dist-info/entry_points.txt
dun-0.1.16.dist-info/RECORD
