Metadata-Version: 2.3
Name: dun
Version: 0.1.16
Summary: Dynamiczny procesor danych z automatycznym wykrywaniem bibliotek
License: MIT
Author: Tom Sapletta
Author-email: info@softreck.dev
Requires-Python: >=3.11,<4.0
Classifier: License :: OSI Approved :: MIT License
Classifier: Programming Language :: Python :: 3
Classifier: Programming Language :: Python :: 3.11
Classifier: Programming Language :: Python :: 3.12
Classifier: Programming Language :: Python :: 3.13
Provides-Extra: ollama
Requires-Dist: aiohttp (>=3.8.6,<4.0.0)
Requires-Dist: fastapi (>=0.104.1,<0.105.0)
Requires-Dist: loguru (>=0.7.2,<0.8.0)
Requires-Dist: numpy (>=1.26.0,<2.0.0)
Requires-Dist: ollama (>=0.1.5,<0.2.0) ; extra == "ollama"
Requires-Dist: pandas (>=2.0.0,<3.0.0)
Requires-Dist: pydantic (>=2.5.0,<3.0.0)
Requires-Dist: pydantic-settings (>=2.1.0,<3.0.0)
Requires-Dist: python-dateutil (>=2.8.2,<3.0.0)
Requires-Dist: python-dotenv (>=1.0.0,<2.0.0)
Requires-Dist: requests (>=2.31.0,<3.0.0)
Requires-Dist: rich (>=13.6.0,<14.0.0)
Requires-Dist: uvicorn[standard] (>=0.24.0,<0.25.0)
